regex2dfa/__init__.py
regex2dfa/core.py
regex2dfa/dfa.py
regex2dfa/formatter.py
regex2dfa/hopcroft.py
regex2dfa/nfa.py
regex2dfa/parser.py
regex2dfa/subset.py
regex2dfa/thompson.py
regex2dfa-0.2.1.dist-info/METADATA
regex2dfa-0.2.1.dist-info/WHEEL
regex2dfa-0.2.1.dist-info/licenses/LICENSE
regex2dfa-0.2.1.dist-info/RECORD
