Metadata-Version: 2.4
Name: regex2dfa
Version: 0.2.1
Summary: Convert regular expressions to minimized DFAs in AT&T FST format
Project-URL: Homepage, https://github.com/kpdyer/regex2dfa
Project-URL: Repository, https://github.com/kpdyer/regex2dfa
Author: Kevin P. Dyer
License-Expression: MIT
License-File: LICENSE
Keywords: automata,dfa,finite-state,fst,nfa,regex
Classifier: Development Status :: 4 - Beta
Classifier: Intended Audience :: Developers
Classifier: License :: OSI Approved :: MIT License
Classifier: Programming Language :: Python :: 3
Classifier: Programming Language :: Python :: 3.8
Classifier: Programming Language :: Python :: 3.9
Classifier: Programming Language :: Python :: 3.10
Classifier: Programming Language :: Python :: 3.11
Classifier: Programming Language :: Python :: 3.12
Classifier: Topic :: Software Development :: Libraries :: Python Modules
Classifier: Topic :: Text Processing
Requires-Python: >=3.8
Provides-Extra: dev
Requires-Dist: pytest>=7.0; extra == 'dev'
